{
  "results": [
    {
      "task": "Task(\n    name='L7_tau0.60_s202_st12_eval:L7:tau0.60:0',\n    inputs_dict={'x': [[-3, -5, -6, 3, -1, -4, -7], [6, 2, 4, -5, -3, 5, 3], [-7, 6, 7, -2, 5, -5, -6], [3, 7, 1, -7, 4, 6, -1], [6, -4, 7, -1, 3, -6, 4]]},\n    outputs=[[-7, -6, -5, -4, -3, -1, 3], [-5, -3, 2, 3, 4, 5, 6], [-7, -6, -5, -2, 5, 6, 7], [-7, -1, 1, 3, 4, 6, 7], [-6, -4, -1, 3, 4, 6, 7]],\n    solution='Sort(x)'\n)",
      "task_solution": "Sort(x)",
      "task_solution_weight": 2,
      "success": true,
      "elapsed_time": 0.0907110889966134,
      "num_unique_values": 39,
      "solution": "Sort(x)",
      "solution_weight": 2,
      "stats": {
        "num_examples": 5,
        "num_inputs": 1,
        "num_values_explored": 211,
        "num_explored_none": 120,
        "num_explored_concrete": 47,
        "num_explored_lambda": 44,
        "num_values_kept": 30,
        "num_kept_concrete": 9,
        "num_kept_lambda": 21,
        "temperature": 1.0,
        "explored_percent_none": 56.872037914691944,
        "explored_percent_concrete": 22.274881516587676,
        "explored_percent_lambda": 20.85308056872038,
        "kept_percent_concrete": 30.0,
        "kept_percent_lambda": 70.0
      }
    },
    {
      "task": "Task(\n    name='L7_tau0.60_s202_st12_eval:L7:tau0.60:1',\n    inputs_dict={'x': [[2, 5, 1, -2, -1, -5, 6], [2, 7, -7, -5, 1, 3, -6], [3, 5, -5, -3, -6, 4, 1], [7, -4, 6, 5, 1, 2, 4], [4, -6, -3, 7, 3, -1, -5]]},\n    outputs=[[-5, -2, -1, 1, 2, 5, 6], [-7, -6, -5, 1, 2, 3, 7], [-6, -5, -3, 1, 3, 4, 5], [-4, 1, 2, 4, 5, 6, 7], [-6, -5, -3, -1, 3, 4, 7]],\n    solution='Sort(x)'\n)",
      "task_solution": "Sort(x)",
      "task_solution_weight": 2,
      "success": true,
      "elapsed_time": 0.09105062700109556,
      "num_unique_values": 39,
      "solution": "Sort(x)",
      "solution_weight": 2,
      "stats": {
        "num_examples": 5,
        "num_inputs": 1,
        "num_values_explored": 211,
        "num_explored_none": 119,
        "num_explored_concrete": 48,
        "num_explored_lambda": 44,
        "num_values_kept": 30,
        "num_kept_concrete": 9,
        "num_kept_lambda": 21,
        "temperature": 1.0,
        "explored_percent_none": 56.39810426540284,
        "explored_percent_concrete": 22.748815165876778,
        "explored_percent_lambda": 20.85308056872038,
        "kept_percent_concrete": 30.0,
        "kept_percent_lambda": 70.0
      }
    },
    {
      "task": "Task(\n    name='L7_tau0.60_s202_st12_eval:L7:tau0.60:2',\n    inputs_dict={'x': [[3, 6, -1, -2, 2, -4, 4], [7, -6, 2, -7, -1, 4, -4], [5, 2, -6, -2, 6, -4, -1], [5, 6, -6, 3, 1, -1, 4], [2, -5, 1, -3, 4, -7, -4]]},\n    outputs=[[-4, -2, -1, 2, 3, 4, 6], [-7, -6, -4, -1, 2, 4, 7], [-6, -4, -2, -1, 2, 5, 6], [-6, -1, 1, 3, 4, 5, 6], [-7, -5, -4, -3, 1, 2, 4]],\n    solution='Sort(x)'\n)",
      "task_solution": "Sort(x)",
      "task_solution_weight": 2,
      "success": true,
      "elapsed_time": 0.09075756999664009,
      "num_unique_values": 39,
      "solution": "Sort(x)",
      "solution_weight": 2,
      "stats": {
        "num_examples": 5,
        "num_inputs": 1,
        "num_values_explored": 211,
        "num_explored_none": 121,
        "num_explored_concrete": 46,
        "num_explored_lambda": 44,
        "num_values_kept": 30,
        "num_kept_concrete": 9,
        "num_kept_lambda": 21,
        "temperature": 1.0,
        "explored_percent_none": 57.345971563981045,
        "explored_percent_concrete": 21.80094786729858,
        "explored_percent_lambda": 20.85308056872038,
        "kept_percent_concrete": 30.0,
        "kept_percent_lambda": 70.0
      }
    },
    {
      "task": "Task(\n    name='L7_tau0.60_s202_st12_eval:L7:tau0.60:3',\n    inputs_dict={'x': [[5, -1, -7, 6, -5, 4, -6], [5, -1, 7, -7, 6, -6, -4], [6, 2, -2, -7, 4, 5, -6], [1, -1, 4, 3, -2, -7, 2], [-1, 6, 4, 1, -7, 5, -5]]},\n    outputs=[[-7, -6, -5, -1, 4, 5, 6], [-7, -6, -4, -1, 5, 6, 7], [-7, -6, -2, 2, 4, 5, 6], [-7, -2, -1, 1, 2, 3, 4], [-7, -5, -1, 1, 4, 5, 6]],\n    solution='Sort(x)'\n)",
      "task_solution": "Sort(x)",
      "task_solution_weight": 2,
      "success": true,
      "elapsed_time": 0.09072547298274003,
      "num_unique_values": 39,
      "solution": "Sort(x)",
      "solution_weight": 2,
      "stats": {
        "num_examples": 5,
        "num_inputs": 1,
        "num_values_explored": 211,
        "num_explored_none": 120,
        "num_explored_concrete": 47,
        "num_explored_lambda": 44,
        "num_values_kept": 30,
        "num_kept_concrete": 9,
        "num_kept_lambda": 21,
        "temperature": 1.0,
        "explored_percent_none": 56.872037914691944,
        "explored_percent_concrete": 22.274881516587676,
        "explored_percent_lambda": 20.85308056872038,
        "kept_percent_concrete": 30.0,
        "kept_percent_lambda": 70.0
      }
    },
    {
      "task": "Task(\n    name='L7_tau0.60_s202_st12_eval:L7:tau0.60:4',\n    inputs_dict={'x': [[6, -7, 3, -4, -1, 1, -2], [2, -5, 6, 5, -6, 3, -2], [5, -5, 1, -6, -1, 7, -7], [-4, 7, -5, -6, -7, 2, -1], [-4, -6, 7, 6, -5, -2, -7]]},\n    outputs=[[-7, -4, -2, -1, 1, 3, 6], [-6, -5, -2, 2, 3, 5, 6], [-7, -6, -5, -1, 1, 5, 7], [-7, -6, -5, -4, -1, 2, 7], [-7, -6, -5, -4, -2, 6, 7]],\n    solution='Sort(x)'\n)",
      "task_solution": "Sort(x)",
      "task_solution_weight": 2,
      "success": true,
      "elapsed_time": 0.09071887499885634,
      "num_unique_values": 39,
      "solution": "Sort(x)",
      "solution_weight": 2,
      "stats": {
        "num_examples": 5,
        "num_inputs": 1,
        "num_values_explored": 211,
        "num_explored_none": 120,
        "num_explored_concrete": 47,
        "num_explored_lambda": 44,
        "num_values_kept": 30,
        "num_kept_concrete": 9,
        "num_kept_lambda": 21,
        "temperature": 1.0,
        "explored_percent_none": 56.872037914691944,
        "explored_percent_concrete": 22.274881516587676,
        "explored_percent_lambda": 20.85308056872038,
        "kept_percent_concrete": 30.0,
        "kept_percent_lambda": 70.0
      }
    },
    {
      "task": "Task(\n    name='L7_tau0.60_s202_st12_eval:L7:tau0.60:5',\n    inputs_dict={'x': [[3, 5, -3, 6, 1, 4, -7], [1, 7, -1, -2, 3, -4, 4], [2, -6, -2, 4, 3, -1, -7], [-1, -4, -3, 6, 7, -7, -5], [4, 1, -1, -7, 7, 3, -4]]},\n    outputs=[[-7, -3, 1, 3, 4, 5, 6], [-4, -2, -1, 1, 3, 4, 7], [-7, -6, -2, -1, 2, 3, 4], [-7, -5, -4, -3, -1, 6, 7], [-7, -4, -1, 1, 3, 4, 7]],\n    solution='Sort(x)'\n)",
      "task_solution": "Sort(x)",
      "task_solution_weight": 2,
      "success": true,
      "elapsed_time": 0.08858386098290794,
      "num_unique_values": 36,
      "solution": "Sort(x)",
      "solution_weight": 2,
      "stats": {
        "num_examples": 5,
        "num_inputs": 1,
        "num_values_explored": 211,
        "num_explored_none": 123,
        "num_explored_concrete": 49,
        "num_explored_lambda": 39,
        "num_values_kept": 27,
        "num_kept_concrete": 9,
        "num_kept_lambda": 18,
        "temperature": 1.0,
        "explored_percent_none": 58.29383886255924,
        "explored_percent_concrete": 23.222748815165875,
        "explored_percent_lambda": 18.48341232227488,
        "kept_percent_concrete": 33.333333333333336,
        "kept_percent_lambda": 66.66666666666667
      }
    },
    {
      "task": "Task(\n    name='L7_tau0.60_s202_st12_eval:L7:tau0.60:6',\n    inputs_dict={'x': [[2, 4, -3, -1, -7, -6, 5], [-3, 3, 2, -7, -4, -5, -1], [3, -4, 4, 5, -1, -5, 1], [2, -4, 5, -2, -7, 3, -3], [1, -3, 4, 6, 3, -7, -2]]},\n    outputs=[[-7, -6, -3, -1, 2, 4, 5], [-7, -5, -4, -3, -1, 2, 3], [-5, -4, -1, 1, 3, 4, 5], [-7, -4, -3, -2, 2, 3, 5], [-7, -3, -2, 1, 3, 4, 6]],\n    solution='Sort(x)'\n)",
      "task_solution": "Sort(x)",
      "task_solution_weight": 2,
      "success": true,
      "elapsed_time": 0.09090392998768948,
      "num_unique_values": 39,
      "solution": "Sort(x)",
      "solution_weight": 2,
      "stats": {
        "num_examples": 5,
        "num_inputs": 1,
        "num_values_explored": 211,
        "num_explored_none": 120,
        "num_explored_concrete": 47,
        "num_explored_lambda": 44,
        "num_values_kept": 30,
        "num_kept_concrete": 9,
        "num_kept_lambda": 21,
        "temperature": 1.0,
        "explored_percent_none": 56.872037914691944,
        "explored_percent_concrete": 22.274881516587676,
        "explored_percent_lambda": 20.85308056872038,
        "kept_percent_concrete": 30.0,
        "kept_percent_lambda": 70.0
      }
    },
    {
      "task": "Task(\n    name='L7_tau0.60_s202_st12_eval:L7:tau0.60:7',\n    inputs_dict={'x': [[-1, -2, 4, -5, 6, 3, -6], [-1, 2, 1, -4, -5, -7, 6], [-3, -5, 4, -4, -7, -6, -1], [7, -4, -5, -2, -1, 3, -6], [4, -6, 1, 5, 2, -7, -3]]},\n    outputs=[[-6, -5, -2, -1, 3, 4, 6], [-7, -5, -4, -1, 1, 2, 6], [-7, -6, -5, -4, -3, -1, 4], [-6, -5, -4, -2, -1, 3, 7], [-7, -6, -3, 1, 2, 4, 5]],\n    solution='Sort(x)'\n)",
      "task_solution": "Sort(x)",
      "task_solution_weight": 2,
      "success": true,
      "elapsed_time": 0.09093420498538762,
      "num_unique_values": 39,
      "solution": "Sort(x)",
      "solution_weight": 2,
      "stats": {
        "num_examples": 5,
        "num_inputs": 1,
        "num_values_explored": 211,
        "num_explored_none": 121,
        "num_explored_concrete": 46,
        "num_explored_lambda": 44,
        "num_values_kept": 30,
        "num_kept_concrete": 9,
        "num_kept_lambda": 21,
        "temperature": 1.0,
        "explored_percent_none": 57.345971563981045,
        "explored_percent_concrete": 21.80094786729858,
        "explored_percent_lambda": 20.85308056872038,
        "kept_percent_concrete": 30.0,
        "kept_percent_lambda": 70.0
      }
    },
    {
      "task": "Task(\n    name='L7_tau0.60_s202_st12_eval:L7:tau0.60:8',\n    inputs_dict={'x': [[-4, 5, -5, -1, -7, 7, -6], [6, 1, 3, -6, 7, 4, -1], [7, 3, -5, -3, -7, 1, 5], [-6, 4, -3, 6, 1, -5, -7], [4, -1, -6, -3, 2, 7, -7]]},\n    outputs=[[-7, -6, -5, -4, -1, 5, 7], [-6, -1, 1, 3, 4, 6, 7], [-7, -5, -3, 1, 3, 5, 7], [-7, -6, -5, -3, 1, 4, 6], [-7, -6, -3, -1, 2, 4, 7]],\n    solution='Sort(x)'\n)",
      "task_solution": "Sort(x)",
      "task_solution_weight": 2,
      "success": true,
      "elapsed_time": 0.09053711500018835,
      "num_unique_values": 39,
      "solution": "Sort(x)",
      "solution_weight": 2,
      "stats": {
        "num_examples": 5,
        "num_inputs": 1,
        "num_values_explored": 211,
        "num_explored_none": 119,
        "num_explored_concrete": 48,
        "num_explored_lambda": 44,
        "num_values_kept": 30,
        "num_kept_concrete": 9,
        "num_kept_lambda": 21,
        "temperature": 1.0,
        "explored_percent_none": 56.39810426540284,
        "explored_percent_concrete": 22.748815165876778,
        "explored_percent_lambda": 20.85308056872038,
        "kept_percent_concrete": 30.0,
        "kept_percent_lambda": 70.0
      }
    },
    {
      "task": "Task(\n    name='L7_tau0.60_s202_st12_eval:L7:tau0.60:9',\n    inputs_dict={'x': [[4, -4, 7, 3, -7, 5, -6], [2, 5, -3, 1, -7, -6, 3], [-7, 5, 3, 6, 2, -6, -2], [5, -1, -2, -5, 2, 7, -4], [-3, 6, 3, -6, -5, 7, -7]]},\n    outputs=[[-7, -6, -4, 3, 4, 5, 7], [-7, -6, -3, 1, 2, 3, 5], [-7, -6, -2, 2, 3, 5, 6], [-5, -4, -2, -1, 2, 5, 7], [-7, -6, -5, -3, 3, 6, 7]],\n    solution='Sort(x)'\n)",
      "task_solution": "Sort(x)",
      "task_solution_weight": 2,
      "success": true,
      "elapsed_time": 0.09123911301139742,
      "num_unique_values": 39,
      "solution": "Sort(x)",
      "solution_weight": 2,
      "stats": {
        "num_examples": 5,
        "num_inputs": 1,
        "num_values_explored": 211,
        "num_explored_none": 119,
        "num_explored_concrete": 48,
        "num_explored_lambda": 44,
        "num_values_kept": 30,
        "num_kept_concrete": 9,
        "num_kept_lambda": 21,
        "temperature": 1.0,
        "explored_percent_none": 56.39810426540284,
        "explored_percent_concrete": 22.748815165876778,
        "explored_percent_lambda": 20.85308056872038,
        "kept_percent_concrete": 30.0,
        "kept_percent_lambda": 70.0
      }
    },
    {
      "task": "Task(\n    name='L7_tau0.60_s202_st12_eval:L7:tau0.60:10',\n    inputs_dict={'x': [[3, -4, 7, 6, -7, 2, -1], [-1, 3, -2, 5, -6, 2, -5], [-2, 4, -7, 7, -1, -6, -3], [6, -4, 7, 4, -5, 5, 2], [6, -4, -3, 1, -1, 4, -6]]},\n    outputs=[[-7, -4, -1, 2, 3, 6, 7], [-6, -5, -2, -1, 2, 3, 5], [-7, -6, -3, -2, -1, 4, 7], [-5, -4, 2, 4, 5, 6, 7], [-6, -4, -3, -1, 1, 4, 6]],\n    solution='Sort(x)'\n)",
      "task_solution": "Sort(x)",
      "task_solution_weight": 2,
      "success": true,
      "elapsed_time": 0.09058935698703863,
      "num_unique_values": 39,
      "solution": "Sort(x)",
      "solution_weight": 2,
      "stats": {
        "num_examples": 5,
        "num_inputs": 1,
        "num_values_explored": 211,
        "num_explored_none": 119,
        "num_explored_concrete": 48,
        "num_explored_lambda": 44,
        "num_values_kept": 30,
        "num_kept_concrete": 9,
        "num_kept_lambda": 21,
        "temperature": 1.0,
        "explored_percent_none": 56.39810426540284,
        "explored_percent_concrete": 22.748815165876778,
        "explored_percent_lambda": 20.85308056872038,
        "kept_percent_concrete": 30.0,
        "kept_percent_lambda": 70.0
      }
    },
    {
      "task": "Task(\n    name='L7_tau0.60_s202_st12_eval:L7:tau0.60:11',\n    inputs_dict={'x': [[5, -4, -5, -2, 1, 4, -6], [3, -6, 1, 6, -7, 2, -4], [1, 2, 6, -1, -6, 3, -3], [4, -1, 6, -7, 3, -6, 1], [-6, 3, 7, 6, -3, -7, -1]]},\n    outputs=[[-6, -5, -4, -2, 1, 4, 5], [-7, -6, -4, 1, 2, 3, 6], [-6, -3, -1, 1, 2, 3, 6], [-7, -6, -1, 1, 3, 4, 6], [-7, -6, -3, -1, 3, 6, 7]],\n    solution='Sort(x)'\n)",
      "task_solution": "Sort(x)",
      "task_solution_weight": 2,
      "success": true,
      "elapsed_time": 0.09070403900113888,
      "num_unique_values": 39,
      "solution": "Sort(x)",
      "solution_weight": 2,
      "stats": {
        "num_examples": 5,
        "num_inputs": 1,
        "num_values_explored": 211,
        "num_explored_none": 119,
        "num_explored_concrete": 48,
        "num_explored_lambda": 44,
        "num_values_kept": 30,
        "num_kept_concrete": 9,
        "num_kept_lambda": 21,
        "temperature": 1.0,
        "explored_percent_none": 56.39810426540284,
        "explored_percent_concrete": 22.748815165876778,
        "explored_percent_lambda": 20.85308056872038,
        "kept_percent_concrete": 30.0,
        "kept_percent_lambda": 70.0
      }
    },
    {
      "task": "Task(\n    name='L7_tau0.60_s202_st12_eval:L7:tau0.60:12',\n    inputs_dict={'x': [[1, -1, 7, -3, -7, -6, 5], [1, 2, -3, 6, -7, 4, -4], [-1, 7, -7, -5, -3, 2, -6], [6, -7, -1, 5, -3, 1, -2], [-5, 6, 7, -2, 1, -1, -6]]},\n    outputs=[[-7, -6, -3, -1, 1, 5, 7], [-7, -4, -3, 1, 2, 4, 6], [-7, -6, -5, -3, -1, 2, 7], [-7, -3, -2, -1, 1, 5, 6], [-6, -5, -2, -1, 1, 6, 7]],\n    solution='Sort(x)'\n)",
      "task_solution": "Sort(x)",
      "task_solution_weight": 2,
      "success": true,
      "elapsed_time": 0.09080216300208122,
      "num_unique_values": 39,
      "solution": "Sort(x)",
      "solution_weight": 2,
      "stats": {
        "num_examples": 5,
        "num_inputs": 1,
        "num_values_explored": 211,
        "num_explored_none": 119,
        "num_explored_concrete": 48,
        "num_explored_lambda": 44,
        "num_values_kept": 30,
        "num_kept_concrete": 9,
        "num_kept_lambda": 21,
        "temperature": 1.0,
        "explored_percent_none": 56.39810426540284,
        "explored_percent_concrete": 22.748815165876778,
        "explored_percent_lambda": 20.85308056872038,
        "kept_percent_concrete": 30.0,
        "kept_percent_lambda": 70.0
      }
    },
    {
      "task": "Task(\n    name='L7_tau0.60_s202_st12_eval:L7:tau0.60:13',\n    inputs_dict={'x': [[3, -3, 5, -2, 1, -6, -1], [1, -3, 3, -1, -4, 2, -2], [-3, 4, 6, -4, 5, 1, -5], [4, -6, 3, -1, -7, -5, 2], [3, -1, -6, -2, 2, -7, 1]]},\n    outputs=[[-6, -3, -2, -1, 1, 3, 5], [-4, -3, -2, -1, 1, 2, 3], [-5, -4, -3, 1, 4, 5, 6], [-7, -6, -5, -1, 2, 3, 4], [-7, -6, -2, -1, 1, 2, 3]],\n    solution='Sort(x)'\n)",
      "task_solution": "Sort(x)",
      "task_solution_weight": 2,
      "success": true,
      "elapsed_time": 0.09095187799539417,
      "num_unique_values": 39,
      "solution": "Sort(x)",
      "solution_weight": 2,
      "stats": {
        "num_examples": 5,
        "num_inputs": 1,
        "num_values_explored": 211,
        "num_explored_none": 119,
        "num_explored_concrete": 48,
        "num_explored_lambda": 44,
        "num_values_kept": 30,
        "num_kept_concrete": 9,
        "num_kept_lambda": 21,
        "temperature": 1.0,
        "explored_percent_none": 56.39810426540284,
        "explored_percent_concrete": 22.748815165876778,
        "explored_percent_lambda": 20.85308056872038,
        "kept_percent_concrete": 30.0,
        "kept_percent_lambda": 70.0
      }
    },
    {
      "task": "Task(\n    name='L7_tau0.60_s202_st12_eval:L7:tau0.60:14',\n    inputs_dict={'x': [[-3, -1, 6, -4, 5, 2, -7], [7, 2, -7, -3, 1, -5, 3], [5, -2, -6, 7, -7, -3, 2], [-7, 5, 7, -4, 3, -1, -6], [2, -5, 7, 1, -7, -6, 5]]},\n    outputs=[[-7, -4, -3, -1, 2, 5, 6], [-7, -5, -3, 1, 2, 3, 7], [-7, -6, -3, -2, 2, 5, 7], [-7, -6, -4, -1, 3, 5, 7], [-7, -6, -5, 1, 2, 5, 7]],\n    solution='Sort(x)'\n)",
      "task_solution": "Sort(x)",
      "task_solution_weight": 2,
      "success": true,
      "elapsed_time": 0.09096992798731662,
      "num_unique_values": 39,
      "solution": "Sort(x)",
      "solution_weight": 2,
      "stats": {
        "num_examples": 5,
        "num_inputs": 1,
        "num_values_explored": 211,
        "num_explored_none": 120,
        "num_explored_concrete": 47,
        "num_explored_lambda": 44,
        "num_values_kept": 30,
        "num_kept_concrete": 9,
        "num_kept_lambda": 21,
        "temperature": 1.0,
        "explored_percent_none": 56.872037914691944,
        "explored_percent_concrete": 22.274881516587676,
        "explored_percent_lambda": 20.85308056872038,
        "kept_percent_concrete": 30.0,
        "kept_percent_lambda": 70.0
      }
    },
    {
      "task": "Task(\n    name='L7_tau0.60_s202_st12_eval:L7:tau0.60:15',\n    inputs_dict={'x': [[-3, 7, 2, 6, -4, -1, 1], [-3, 7, -2, 4, 2, -6, 1], [7, 1, -3, -5, 4, 6, -1], [7, 3, -3, 2, -5, -2, 4], [6, 4, -1, 7, -6, -5, 5]]},\n    outputs=[[-4, -3, -1, 1, 2, 6, 7], [-6, -3, -2, 1, 2, 4, 7], [-5, -3, -1, 1, 4, 6, 7], [-5, -3, -2, 2, 3, 4, 7], [-6, -5, -1, 4, 5, 6, 7]],\n    solution='Sort(x)'\n)",
      "task_solution": "Sort(x)",
      "task_solution_weight": 2,
      "success": true,
      "elapsed_time": 0.09048467900720425,
      "num_unique_values": 39,
      "solution": "Sort(x)",
      "solution_weight": 2,
      "stats": {
        "num_examples": 5,
        "num_inputs": 1,
        "num_values_explored": 211,
        "num_explored_none": 120,
        "num_explored_concrete": 47,
        "num_explored_lambda": 44,
        "num_values_kept": 30,
        "num_kept_concrete": 9,
        "num_kept_lambda": 21,
        "temperature": 1.0,
        "explored_percent_none": 56.872037914691944,
        "explored_percent_concrete": 22.274881516587676,
        "explored_percent_lambda": 20.85308056872038,
        "kept_percent_concrete": 30.0,
        "kept_percent_lambda": 70.0
      }
    },
    {
      "task": "Task(\n    name='L7_tau0.60_s202_st12_eval:L7:tau0.60:16',\n    inputs_dict={'x': [[-3, -7, 2, 1, -4, -6, -5], [7, 2, -3, -4, 4, 5, 1], [6, -3, -5, 7, 1, -7, -2], [5, -5, 2, -2, -7, 3, -3], [-1, -6, 7, 4, 2, -7, -2]]},\n    outputs=[[-7, -6, -5, -4, -3, 1, 2], [-4, -3, 1, 2, 4, 5, 7], [-7, -5, -3, -2, 1, 6, 7], [-7, -5, -3, -2, 2, 3, 5], [-7, -6, -2, -1, 2, 4, 7]],\n    solution='Sort(x)'\n)",
      "task_solution": "Sort(x)",
      "task_solution_weight": 2,
      "success": true,
      "elapsed_time": 0.09087449399521574,
      "num_unique_values": 39,
      "solution": "Sort(x)",
      "solution_weight": 2,
      "stats": {
        "num_examples": 5,
        "num_inputs": 1,
        "num_values_explored": 211,
        "num_explored_none": 120,
        "num_explored_concrete": 47,
        "num_explored_lambda": 44,
        "num_values_kept": 30,
        "num_kept_concrete": 9,
        "num_kept_lambda": 21,
        "temperature": 1.0,
        "explored_percent_none": 56.872037914691944,
        "explored_percent_concrete": 22.274881516587676,
        "explored_percent_lambda": 20.85308056872038,
        "kept_percent_concrete": 30.0,
        "kept_percent_lambda": 70.0
      }
    },
    {
      "task": "Task(\n    name='L7_tau0.60_s202_st12_eval:L7:tau0.60:17',\n    inputs_dict={'x': [[6, 7, -7, 1, -4, -3, 4], [2, -3, 5, -6, 6, -1, -7], [1, 5, -2, -4, 4, 7, -5], [4, -3, -1, -4, 5, -7, 3], [4, 7, -4, 1, -6, -5, 6]]},\n    outputs=[[-7, -4, -3, 1, 4, 6, 7], [-7, -6, -3, -1, 2, 5, 6], [-5, -4, -2, 1, 4, 5, 7], [-7, -4, -3, -1, 3, 4, 5], [-6, -5, -4, 1, 4, 6, 7]],\n    solution='Sort(x)'\n)",
      "task_solution": "Sort(x)",
      "task_solution_weight": 2,
      "success": true,
      "elapsed_time": 0.09066975500900298,
      "num_unique_values": 39,
      "solution": "Sort(x)",
      "solution_weight": 2,
      "stats": {
        "num_examples": 5,
        "num_inputs": 1,
        "num_values_explored": 211,
        "num_explored_none": 118,
        "num_explored_concrete": 49,
        "num_explored_lambda": 44,
        "num_values_kept": 30,
        "num_kept_concrete": 9,
        "num_kept_lambda": 21,
        "temperature": 1.0,
        "explored_percent_none": 55.92417061611374,
        "explored_percent_concrete": 23.222748815165875,
        "explored_percent_lambda": 20.85308056872038,
        "kept_percent_concrete": 30.0,
        "kept_percent_lambda": 70.0
      }
    },
    {
      "task": "Task(\n    name='L7_tau0.60_s202_st12_eval:L7:tau0.60:18',\n    inputs_dict={'x': [[7, -5, -3, 4, 6, 1, -6], [5, 1, 6, -6, -3, -4, 2], [3, -4, 5, 4, 7, -2, -6], [5, 6, -5, 1, -4, 2, -2], [7, -2, -1, 2, 1, 5, -7]]},\n    outputs=[[-6, -5, -3, 1, 4, 6, 7], [-6, -4, -3, 1, 2, 5, 6], [-6, -4, -2, 3, 4, 5, 7], [-5, -4, -2, 1, 2, 5, 6], [-7, -2, -1, 1, 2, 5, 7]],\n    solution='Sort(x)'\n)",
      "task_solution": "Sort(x)",
      "task_solution_weight": 2,
      "success": true,
      "elapsed_time": 0.09096385099110194,
      "num_unique_values": 39,
      "solution": "Sort(x)",
      "solution_weight": 2,
      "stats": {
        "num_examples": 5,
        "num_inputs": 1,
        "num_values_explored": 211,
        "num_explored_none": 120,
        "num_explored_concrete": 47,
        "num_explored_lambda": 44,
        "num_values_kept": 30,
        "num_kept_concrete": 9,
        "num_kept_lambda": 21,
        "temperature": 1.0,
        "explored_percent_none": 56.872037914691944,
        "explored_percent_concrete": 22.274881516587676,
        "explored_percent_lambda": 20.85308056872038,
        "kept_percent_concrete": 30.0,
        "kept_percent_lambda": 70.0
      }
    },
    {
      "task": "Task(\n    name='L7_tau0.60_s202_st12_eval:L7:tau0.60:19',\n    inputs_dict={'x': [[-7, 7, -4, 6, 5, -1, -5], [3, -1, -2, 6, 7, -4, -3], [2, 4, -3, 7, -6, 6, -7], [4, -4, -1, 5, 2, -3, -2], [-7, 6, -1, 5, 3, 1, -3]]},\n    outputs=[[-7, -5, -4, -1, 5, 6, 7], [-4, -3, -2, -1, 3, 6, 7], [-7, -6, -3, 2, 4, 6, 7], [-4, -3, -2, -1, 2, 4, 5], [-7, -3, -1, 1, 3, 5, 6]],\n    solution='Sort(x)'\n)",
      "task_solution": "Sort(x)",
      "task_solution_weight": 2,
      "success": true,
      "elapsed_time": 0.0907931620022282,
      "num_unique_values": 39,
      "solution": "Sort(x)",
      "solution_weight": 2,
      "stats": {
        "num_examples": 5,
        "num_inputs": 1,
        "num_values_explored": 211,
        "num_explored_none": 118,
        "num_explored_concrete": 49,
        "num_explored_lambda": 44,
        "num_values_kept": 30,
        "num_kept_concrete": 9,
        "num_kept_lambda": 21,
        "temperature": 1.0,
        "explored_percent_none": 55.92417061611374,
        "explored_percent_concrete": 23.222748815165875,
        "explored_percent_lambda": 20.85308056872038,
        "kept_percent_concrete": 30.0,
        "kept_percent_lambda": 70.0
      }
    },
    {
      "task": "Task(\n    name='L7_tau0.60_s202_st12_eval:L7:tau0.60:20',\n    inputs_dict={'x': [[6, -1, -3, 2, 3, 4, -7], [-3, 6, 7, 5, -2, -7, 3], [4, 7, -5, -7, 5, 6, -6], [6, -6, 1, -3, -1, 4, -7], [-4, 5, 2, -3, -5, -7, 7]]},\n    outputs=[[-7, -3, -1, 2, 3, 4, 6], [-7, -3, -2, 3, 5, 6, 7], [-7, -6, -5, 4, 5, 6, 7], [-7, -6, -3, -1, 1, 4, 6], [-7, -5, -4, -3, 2, 5, 7]],\n    solution='Sort(x)'\n)",
      "task_solution": "Sort(x)",
      "task_solution_weight": 2,
      "success": true,
      "elapsed_time": 0.09126917799585499,
      "num_unique_values": 39,
      "solution": "Sort(x)",
      "solution_weight": 2,
      "stats": {
        "num_examples": 5,
        "num_inputs": 1,
        "num_values_explored": 211,
        "num_explored_none": 119,
        "num_explored_concrete": 48,
        "num_explored_lambda": 44,
        "num_values_kept": 30,
        "num_kept_concrete": 9,
        "num_kept_lambda": 21,
        "temperature": 1.0,
        "explored_percent_none": 56.39810426540284,
        "explored_percent_concrete": 22.748815165876778,
        "explored_percent_lambda": 20.85308056872038,
        "kept_percent_concrete": 30.0,
        "kept_percent_lambda": 70.0
      }
    },
    {
      "task": "Task(\n    name='L7_tau0.60_s202_st12_eval:L7:tau0.60:21',\n    inputs_dict={'x': [[7, -5, -2, 5, 4, -6, 2], [6, 5, -6, 2, -7, -4, 7], [5, 2, -2, -1, 6, -5, 3], [-2, 3, 4, 6, -1, 2, -5], [-6, 6, -3, 5, 3, 2, -4]]},\n    outputs=[[-6, -5, -2, 2, 4, 5, 7], [-7, -6, -4, 2, 5, 6, 7], [-5, -2, -1, 2, 3, 5, 6], [-5, -2, -1, 2, 3, 4, 6], [-6, -4, -3, 2, 3, 5, 6]],\n    solution='Sort(x)'\n)",
      "task_solution": "Sort(x)",
      "task_solution_weight": 2,
      "success": true,
      "elapsed_time": 0.09140570799354464,
      "num_unique_values": 39,
      "solution": "Sort(x)",
      "solution_weight": 2,
      "stats": {
        "num_examples": 5,
        "num_inputs": 1,
        "num_values_explored": 211,
        "num_explored_none": 118,
        "num_explored_concrete": 49,
        "num_explored_lambda": 44,
        "num_values_kept": 30,
        "num_kept_concrete": 9,
        "num_kept_lambda": 21,
        "temperature": 1.0,
        "explored_percent_none": 55.92417061611374,
        "explored_percent_concrete": 23.222748815165875,
        "explored_percent_lambda": 20.85308056872038,
        "kept_percent_concrete": 30.0,
        "kept_percent_lambda": 70.0
      }
    },
    {
      "task": "Task(\n    name='L7_tau0.60_s202_st12_eval:L7:tau0.60:22',\n    inputs_dict={'x': [[-1, 1, -5, -3, -7, -6, 6], [-5, 2, 6, 7, 1, -3, -7], [4, 3, 1, 2, -7, -5, 7], [6, -6, 2, -1, -5, -3, 1], [5, 1, 4, -7, -5, -3, 3]]},\n    outputs=[[-7, -6, -5, -3, -1, 1, 6], [-7, -5, -3, 1, 2, 6, 7], [-7, -5, 1, 2, 3, 4, 7], [-6, -5, -3, -1, 1, 2, 6], [-7, -5, -3, 1, 3, 4, 5]],\n    solution='Sort(x)'\n)",
      "task_solution": "Sort(x)",
      "task_solution_weight": 2,
      "success": true,
      "elapsed_time": 0.09163197298767045,
      "num_unique_values": 39,
      "solution": "Sort(x)",
      "solution_weight": 2,
      "stats": {
        "num_examples": 5,
        "num_inputs": 1,
        "num_values_explored": 211,
        "num_explored_none": 120,
        "num_explored_concrete": 47,
        "num_explored_lambda": 44,
        "num_values_kept": 30,
        "num_kept_concrete": 9,
        "num_kept_lambda": 21,
        "temperature": 1.0,
        "explored_percent_none": 56.872037914691944,
        "explored_percent_concrete": 22.274881516587676,
        "explored_percent_lambda": 20.85308056872038,
        "kept_percent_concrete": 30.0,
        "kept_percent_lambda": 70.0
      }
    },
    {
      "task": "Task(\n    name='L7_tau0.60_s202_st12_eval:L7:tau0.60:23',\n    inputs_dict={'x': [[2, -4, 1, 6, 3, -6, -2], [-7, 5, 3, -5, -1, -3, -6], [1, 3, 7, 2, -6, 6, -7], [-4, 5, -2, 3, 2, -6, -1], [5, 3, -2, -6, -3, 6, -1]]},\n    outputs=[[-6, -4, -2, 1, 2, 3, 6], [-7, -6, -5, -3, -1, 3, 5], [-7, -6, 1, 2, 3, 6, 7], [-6, -4, -2, -1, 2, 3, 5], [-6, -3, -2, -1, 3, 5, 6]],\n    solution='Sort(x)'\n)",
      "task_solution": "Sort(x)",
      "task_solution_weight": 2,
      "success": true,
      "elapsed_time": 0.09065813198685646,
      "num_unique_values": 39,
      "solution": "Sort(x)",
      "solution_weight": 2,
      "stats": {
        "num_examples": 5,
        "num_inputs": 1,
        "num_values_explored": 211,
        "num_explored_none": 120,
        "num_explored_concrete": 47,
        "num_explored_lambda": 44,
        "num_values_kept": 30,
        "num_kept_concrete": 9,
        "num_kept_lambda": 21,
        "temperature": 1.0,
        "explored_percent_none": 56.872037914691944,
        "explored_percent_concrete": 22.274881516587676,
        "explored_percent_lambda": 20.85308056872038,
        "kept_percent_concrete": 30.0,
        "kept_percent_lambda": 70.0
      }
    },
    {
      "task": "Task(\n    name='L7_tau0.60_s202_st12_eval:L7:tau0.60:24',\n    inputs_dict={'x': [[3, -3, -4, 2, 1, 7, -5], [5, 7, -6, 3, -7, 6, -1], [-6, 7, 5, -3, 3, -4, -1], [5, -3, 3, -1, 6, 4, -4], [1, -2, 5, 2, -6, 6, -7]]},\n    outputs=[[-5, -4, -3, 1, 2, 3, 7], [-7, -6, -1, 3, 5, 6, 7], [-6, -4, -3, -1, 3, 5, 7], [-4, -3, -1, 3, 4, 5, 6], [-7, -6, -2, 1, 2, 5, 6]],\n    solution='Sort(x)'\n)",
      "task_solution": "Sort(x)",
      "task_solution_weight": 2,
      "success": true,
      "elapsed_time": 0.09052599899587221,
      "num_unique_values": 39,
      "solution": "Sort(x)",
      "solution_weight": 2,
      "stats": {
        "num_examples": 5,
        "num_inputs": 1,
        "num_values_explored": 211,
        "num_explored_none": 119,
        "num_explored_concrete": 48,
        "num_explored_lambda": 44,
        "num_values_kept": 30,
        "num_kept_concrete": 9,
        "num_kept_lambda": 21,
        "temperature": 1.0,
        "explored_percent_none": 56.39810426540284,
        "explored_percent_concrete": 22.748815165876778,
        "explored_percent_lambda": 20.85308056872038,
        "kept_percent_concrete": 30.0,
        "kept_percent_lambda": 70.0
      }
    },
    {
      "task": "Task(\n    name='L7_tau0.60_s202_st12_eval:L7:tau0.60:25',\n    inputs_dict={'x': [[5, -4, -2, 4, -1, -7, 1], [-3, 2, 3, 1, -4, 5, -7], [4, 5, -2, 6, 7, -5, -3], [3, 6, -2, -4, 1, -7, 4], [5, 3, -6, 2, -7, -2, 6]]},\n    outputs=[[-7, -4, -2, -1, 1, 4, 5], [-7, -4, -3, 1, 2, 3, 5], [-5, -3, -2, 4, 5, 6, 7], [-7, -4, -2, 1, 3, 4, 6], [-7, -6, -2, 2, 3, 5, 6]],\n    solution='Sort(x)'\n)",
      "task_solution": "Sort(x)",
      "task_solution_weight": 2,
      "success": true,
      "elapsed_time": 0.09169721798389219,
      "num_unique_values": 39,
      "solution": "Sort(x)",
      "solution_weight": 2,
      "stats": {
        "num_examples": 5,
        "num_inputs": 1,
        "num_values_explored": 211,
        "num_explored_none": 119,
        "num_explored_concrete": 48,
        "num_explored_lambda": 44,
        "num_values_kept": 30,
        "num_kept_concrete": 9,
        "num_kept_lambda": 21,
        "temperature": 1.0,
        "explored_percent_none": 56.39810426540284,
        "explored_percent_concrete": 22.748815165876778,
        "explored_percent_lambda": 20.85308056872038,
        "kept_percent_concrete": 30.0,
        "kept_percent_lambda": 70.0
      }
    },
    {
      "task": "Task(\n    name='L7_tau0.60_s202_st12_eval:L7:tau0.60:26',\n    inputs_dict={'x': [[3, -6, -2, 7, -3, 1, -4], [7, -6, 2, -3, -5, -7, 6], [5, -6, 7, -7, 2, -1, -3], [7, -6, -7, 5, -2, -3, -5], [5, -6, 6, 7, -1, -7, 3]]},\n    outputs=[[-6, -4, -3, -2, 1, 3, 7], [-7, -6, -5, -3, 2, 6, 7], [-7, -6, -3, -1, 2, 5, 7], [-7, -6, -5, -3, -2, 5, 7], [-7, -6, -1, 3, 5, 6, 7]],\n    solution='Sort(x)'\n)",
      "task_solution": "Sort(x)",
      "task_solution_weight": 2,
      "success": true,
      "elapsed_time": 0.09740646599675529,
      "num_unique_values": 39,
      "solution": "Sort(x)",
      "solution_weight": 2,
      "stats": {
        "num_examples": 5,
        "num_inputs": 1,
        "num_values_explored": 211,
        "num_explored_none": 119,
        "num_explored_concrete": 48,
        "num_explored_lambda": 44,
        "num_values_kept": 30,
        "num_kept_concrete": 9,
        "num_kept_lambda": 21,
        "temperature": 1.0,
        "explored_percent_none": 56.39810426540284,
        "explored_percent_concrete": 22.748815165876778,
        "explored_percent_lambda": 20.85308056872038,
        "kept_percent_concrete": 30.0,
        "kept_percent_lambda": 70.0
      }
    },
    {
      "task": "Task(\n    name='L7_tau0.60_s202_st12_eval:L7:tau0.60:27',\n    inputs_dict={'x': [[-4, 7, 5, -5, 3, 2, -3], [7, -4, 4, 1, -7, 6, 2], [-1, -2, 2, 6, -3, 5, -4], [-3, -6, 6, 1, -5, 4, -7], [-4, 7, 1, -5, -2, -7, 5]]},\n    outputs=[[-5, -4, -3, 2, 3, 5, 7], [-7, -4, 1, 2, 4, 6, 7], [-4, -3, -2, -1, 2, 5, 6], [-7, -6, -5, -3, 1, 4, 6], [-7, -5, -4, -2, 1, 5, 7]],\n    solution='Sort(x)'\n)",
      "task_solution": "Sort(x)",
      "task_solution_weight": 2,
      "success": true,
      "elapsed_time": 0.091249313991284,
      "num_unique_values": 39,
      "solution": "Sort(x)",
      "solution_weight": 2,
      "stats": {
        "num_examples": 5,
        "num_inputs": 1,
        "num_values_explored": 211,
        "num_explored_none": 120,
        "num_explored_concrete": 47,
        "num_explored_lambda": 44,
        "num_values_kept": 30,
        "num_kept_concrete": 9,
        "num_kept_lambda": 21,
        "temperature": 1.0,
        "explored_percent_none": 56.872037914691944,
        "explored_percent_concrete": 22.274881516587676,
        "explored_percent_lambda": 20.85308056872038,
        "kept_percent_concrete": 30.0,
        "kept_percent_lambda": 70.0
      }
    },
    {
      "task": "Task(\n    name='L7_tau0.60_s202_st12_eval:L7:tau0.60:28',\n    inputs_dict={'x': [[6, -4, 3, -6, 7, 1, -2], [6, 3, -6, 4, -4, -7, 7], [-2, 3, -5, -4, -3, -7, 2], [3, 2, 7, -5, 5, 6, -6], [2, 1, 7, -2, 5, -4, 3]]},\n    outputs=[[-6, -4, -2, 1, 3, 6, 7], [-7, -6, -4, 3, 4, 6, 7], [-7, -5, -4, -3, -2, 2, 3], [-6, -5, 2, 3, 5, 6, 7], [-4, -2, 1, 2, 3, 5, 7]],\n    solution='Sort(x)'\n)",
      "task_solution": "Sort(x)",
      "task_solution_weight": 2,
      "success": true,
      "elapsed_time": 0.09102841099957004,
      "num_unique_values": 39,
      "solution": "Sort(x)",
      "solution_weight": 2,
      "stats": {
        "num_examples": 5,
        "num_inputs": 1,
        "num_values_explored": 211,
        "num_explored_none": 119,
        "num_explored_concrete": 48,
        "num_explored_lambda": 44,
        "num_values_kept": 30,
        "num_kept_concrete": 9,
        "num_kept_lambda": 21,
        "temperature": 1.0,
        "explored_percent_none": 56.39810426540284,
        "explored_percent_concrete": 22.748815165876778,
        "explored_percent_lambda": 20.85308056872038,
        "kept_percent_concrete": 30.0,
        "kept_percent_lambda": 70.0
      }
    },
    {
      "task": "Task(\n    name='L7_tau0.60_s202_st12_eval:L7:tau0.60:29',\n    inputs_dict={'x': [[-5, 7, -4, 4, -2, 3, -6], [1, -7, -3, -4, 4, -6, -5], [-2, 7, 4, -4, 5, -6, 1], [7, -6, -2, -3, -7, -4, 5], [-3, 7, -1, 1, -4, 3, -5]]},\n    outputs=[[-6, -5, -4, -2, 3, 4, 7], [-7, -6, -5, -4, -3, 1, 4], [-6, -4, -2, 1, 4, 5, 7], [-7, -6, -4, -3, -2, 5, 7], [-5, -4, -3, -1, 1, 3, 7]],\n    solution='Sort(x)'\n)",
      "task_solution": "Sort(x)",
      "task_solution_weight": 2,
      "success": true,
      "elapsed_time": 0.09108147397637367,
      "num_unique_values": 39,
      "solution": "Sort(x)",
      "solution_weight": 2,
      "stats": {
        "num_examples": 5,
        "num_inputs": 1,
        "num_values_explored": 211,
        "num_explored_none": 119,
        "num_explored_concrete": 48,
        "num_explored_lambda": 44,
        "num_values_kept": 30,
        "num_kept_concrete": 9,
        "num_kept_lambda": 21,
        "temperature": 1.0,
        "explored_percent_none": 56.39810426540284,
        "explored_percent_concrete": 22.748815165876778,
        "explored_percent_lambda": 20.85308056872038,
        "kept_percent_concrete": 30.0,
        "kept_percent_lambda": 70.0
      }
    }
  ],
  "num_tasks": 30,
  "num_tasks_solved": 30,
  "success_rate": 1.0
}